Metadata-Version: 2.1
Name: changshi
Version: 0.1.0
Summary: Implementations for Commonsense Knowledge and Reasoning
Home-page: https://github.com/benjaminbeilharz/changshi
Author: Benjamin Beilharz
Author-email: benjamin.beilharz@pm.me
License: Apache
Keywords: nlp
Classifier: Intended Audience :: Science/Research
Classifier: Development Status :: 3 - Alpha
Classifier: License :: OSI Approved :: Apache Software License
Classifier: Programming Language :: Python :: 3
Classifier: Topic :: Scientific/Engineering :: Artificial Intelligence
Requires-Python: >=3.7
Provides-Extra: dev
License-File: LICENSE
